setup.py
src/nt3core/__init__.py
src/nt3core.egg-info/PKG-INFO
src/nt3core.egg-info/SOURCES.txt
src/nt3core.egg-info/dependency_links.txt
src/nt3core.egg-info/requires.txt
src/nt3core.egg-info/top_level.txt
src/nt3core/logger/__init__.py
src/nt3core/logger/log.py
src/nt3core/logger/log_context.py
src/nt3core/logger/logger_config.py