Metadata-Version: 2.1
Name: nt3core
Version: 0.0.3
Summary: Core Library for NovaTouch 3
Author: novacom software GmbH
